[
  {
    "ContainingType": "Auth.Api.Controllers.AdministrationController",
    "Method": "AddNewRole",
    "RelativePath": "api/Administration/AddNewRole",
    "HttpMethod": "POST",
    "IsController": true,
    "Order": 0,
    "Parameters": [
      {
        "Name": "roleName",
        "Type": "System.String",
        "IsRequired": false
      }
    ],
    "ReturnTypes": []
  },
  {
    "ContainingType": "Auth.Api.Controllers.AdministrationController",
    "Method": "AssignAccess",
    "RelativePath": "api/Administration/AssignAccess",
    "HttpMethod": "POST",
    "IsController": true,
    "Order": 0,
    "Parameters": [
      {
        "Name": "dto",
        "Type": "Auth.Api.Modal.AssignAccessDto",
        "IsRequired": true
      }
    ],
    "ReturnTypes": []
  },
  {
    "ContainingType": "Auth.Api.Controllers.AdministrationController",
    "Method": "GetAllRoles",
    "RelativePath": "api/Administration/GetAllRoles",
    "HttpMethod": "GET",
    "IsController": true,
    "Order": 0,
    "Parameters": [],
    "ReturnTypes": []
  },
  {
    "ContainingType": "Auth.Api.Controllers.AdministrationController",
    "Method": "GetAppContentByRole",
    "RelativePath": "api/Administration/GetAppContentByRole",
    "HttpMethod": "GET",
    "IsController": true,
    "Order": 0,
    "Parameters": [
      {
        "Name": "roleName",
        "Type": "System.String",
        "IsRequired": false
      }
    ],
    "ReturnTypes": []
  },
  {
    "ContainingType": "Auth.Api.Controllers.AdministrationController",
    "Method": "GetMenuItem",
    "RelativePath": "api/Administration/GetMenuItem",
    "HttpMethod": "GET",
    "IsController": true,
    "Order": 0,
    "Parameters": [
      {
        "Name": "userName",
        "Type": "System.String",
        "IsRequired": false
      }
    ],
    "ReturnTypes": []
  },
  {
    "ContainingType": "Auth.Api.Controllers.UserController",
    "Method": "Authenticate",
    "RelativePath": "api/User/authenticate",
    "HttpMethod": "POST",
    "IsController": true,
    "Order": 0,
    "Parameters": [
      {
        "Name": "userObj",
        "Type": "Auth.Api.Modal.UserCred",
        "IsRequired": true
      }
    ],
    "ReturnTypes": []
  },
  {
    "ContainingType": "Auth.Api.Controllers.UserController",
    "Method": "GetAllUsers",
    "RelativePath": "api/User/GetAllUsers",
    "HttpMethod": "GET",
    "IsController": true,
    "Order": 0,
    "Parameters": [],
    "ReturnTypes": [
      {
        "Type": "Auth.Api.Data.Entties.User",
        "MediaTypes": [
          "text/plain",
          "application/json",
          "text/json"
        ],
        "StatusCode": 200
      }
    ]
  },
  {
    "ContainingType": "Auth.Api.Controllers.UserController",
    "Method": "Refresh",
    "RelativePath": "api/User/refresh",
    "HttpMethod": "POST",
    "IsController": true,
    "Order": 0,
    "Parameters": [
      {
        "Name": "tokenApiDto",
        "Type": "Auth.Api.Modal.TokenApiDto",
        "IsRequired": true
      }
    ],
    "ReturnTypes": []
  },
  {
    "ContainingType": "Auth.Api.Controllers.UserController",
    "Method": "AddUser",
    "RelativePath": "api/User/register",
    "HttpMethod": "POST",
    "IsController": true,
    "Order": 0,
    "Parameters": [
      {
        "Name": "userObj",
        "Type": "Auth.Api.Data.Entties.User",
        "IsRequired": true
      }
    ],
    "ReturnTypes": []
  }
]